setup.py
wechatpyyyy/__init__.py
wechatpyyyy/_compat.py
wechatpyyyy/component.py
wechatpyyyy/constants.py
wechatpyyyy/events.py
wechatpyyyy/exceptions.py
wechatpyyyy/fields.py
wechatpyyyy/messages.py
wechatpyyyy/oauth.py
wechatpyyyy/parser.py
wechatpyyyy/replies.py
wechatpyyyy/utils.py
wechatpyyyy.egg-info/PKG-INFO
wechatpyyyy.egg-info/SOURCES.txt
wechatpyyyy.egg-info/dependency_links.txt
wechatpyyyy.egg-info/requires.txt
wechatpyyyy.egg-info/top_level.txt
wechatpyyyy/client/__init__.py
wechatpyyyy/client/base.py
wechatpyyyy/client/api/__init__.py
wechatpyyyy/client/api/base.py
wechatpyyyy/client/api/card.py
wechatpyyyy/client/api/cloud.py
wechatpyyyy/client/api/customservice.py
wechatpyyyy/client/api/datacube.py
wechatpyyyy/client/api/device.py
wechatpyyyy/client/api/group.py
wechatpyyyy/client/api/invoice.py
wechatpyyyy/client/api/jsapi.py
wechatpyyyy/client/api/marketing.py
wechatpyyyy/client/api/material.py
wechatpyyyy/client/api/media.py
wechatpyyyy/client/api/menu.py
wechatpyyyy/client/api/message.py
wechatpyyyy/client/api/misc.py
wechatpyyyy/client/api/poi.py
wechatpyyyy/client/api/qrcode.py
wechatpyyyy/client/api/scan.py
wechatpyyyy/client/api/semantic.py
wechatpyyyy/client/api/shakearound.py
wechatpyyyy/client/api/tag.py
wechatpyyyy/client/api/template.py
wechatpyyyy/client/api/user.py
wechatpyyyy/client/api/wifi.py
wechatpyyyy/client/api/wxa.py
wechatpyyyy/client/api/merchant/__init__.py
wechatpyyyy/client/api/merchant/category.py
wechatpyyyy/client/api/merchant/common.py
wechatpyyyy/client/api/merchant/express.py
wechatpyyyy/client/api/merchant/group.py
wechatpyyyy/client/api/merchant/order.py
wechatpyyyy/client/api/merchant/shelf.py
wechatpyyyy/client/api/merchant/stock.py
wechatpyyyy/crypto/__init__.py
wechatpyyyy/crypto/base.py
wechatpyyyy/crypto/cryptography.py
wechatpyyyy/crypto/pkcs7.py
wechatpyyyy/crypto/pycrypto.py
wechatpyyyy/enterprise/__init__.py
wechatpyyyy/enterprise/crypto.py
wechatpyyyy/enterprise/events.py
wechatpyyyy/enterprise/exceptions.py
wechatpyyyy/enterprise/messages.py
wechatpyyyy/enterprise/parser.py
wechatpyyyy/enterprise/replies.py
wechatpyyyy/enterprise/client/__init__.py
