Metadata-Version: 2.1
Name: wechatpyyyy
Version: 0.0.7
Summary: 修改了一下request verify=false
Home-page: UNKNOWN
Author: xiaozhouzhou
Author-email: zhoudabaoonline@gmail.com
License: MIT Licence
Keywords: pip,wechatpyyyy
Platform: any
